Metadata-Version: 2.1
Name: pypatternfinder
Version: 1.0.1
Summary: Signature matcher/wildcard pattern finder.
Home-page: https://www.github.com/FaithBeam/pypatternfinder
Author: FaithBeam
Author-email: pigeonhopper68@gmail.com
License: MIT
Platform: UNKNOWN
